prelude_cli_beta/__init__.py
prelude_cli_beta/cli.py
prelude_cli_beta/templates/__init__.py
prelude_cli_beta/views/__init__.py
prelude_cli_beta/views/auth.py
prelude_cli_beta/views/build.py
prelude_cli_beta/views/configure.py
prelude_cli_beta/views/detect.py
prelude_cli_beta/views/generate.py
prelude_cli_beta/views/iam.py
prelude_cli_beta/views/jobs.py
prelude_cli_beta/views/partner.py
prelude_cli_beta/views/scm.py
prelude_cli_beta/views/shared.py
prelude_cli_beta-1467.dist-info/licenses/LICENSE
prelude_cli_beta-1467.dist-info/METADATA
prelude_cli_beta-1467.dist-info/WHEEL
prelude_cli_beta-1467.dist-info/entry_points.txt
prelude_cli_beta-1467.dist-info/top_level.txt
prelude_cli_beta-1467.dist-info/RECORD
