Metadata-Version: 2.4
Name: prelude-cli-beta
Version: 1467
Summary: For interacting with the Prelude SDK
Home-page: https://github.com/preludeorg
Author: Prelude Research
Author-email: support@preludesecurity.com
Classifier: Programming Language :: Python :: 3
Classifier: License :: OSI Approved :: MIT License
Classifier: Operating System :: OS Independent
Requires-Python: >=3.10
License-File: LICENSE
Requires-Dist: prelude-sdk-beta==1467
Requires-Dist: click>8
Requires-Dist: rich
Requires-Dist: python-dateutil
Requires-Dist: pyyaml
Dynamic: license-file
